vdataset/__init__.py
vdataset/labelmap.py
vdataset/vdataset.py
vdataset-0.0.5.dist-info/LICENSE
vdataset-0.0.5.dist-info/METADATA
vdataset-0.0.5.dist-info/WHEEL
vdataset-0.0.5.dist-info/top_level.txt
vdataset-0.0.5.dist-info/RECORD
