Metadata-Version: 2.1
Name: vdataset
Version: 0.0.5
Summary: Load video datasets to PyTorch DataLoader and generate label maps
Home-page: https://github.com/nzx9/VDataset
Author: Navindu Dananga
Author-email: navindum@protonmail.com
License: MIT
Platform: UNKNOWN
Classifier: Programming Language :: Python :: 3
Classifier: License :: OSI Approved :: MIT License
Classifier: Operating System :: OS Independent
Requires-Python: >=3.6
Requires-Dist: pandas
Requires-Dist: Pillow
Requires-Dist: torch
